api
embeddings
etnlp_api
utils
visualizer
