Metadata-Version: 2.1
Name: ETNLP
Version: 0.1.1
Summary: ETNLP: Embedding Toolkit for NLP Tasks
Home-page: https://github.com/vietnlp/etnlp
Author: vietnlp
Author-email: sonvx.coltech@gmail.com
License: MIT
Platform: UNKNOWN
